rpg_dice_roller/__init__.py
rpg_dice_roller/src/__init__.py
rpg_dice_roller/src/main.py
rpg_dice_roller/src/functions/__init__.py
rpg_dice_roller/src/functions/dice_roll.py
rpg_dice_roller/src/functions/statistics.py
rpg_dice_roller/src/models/__init__.py
rpg_dice_roller/src/models/dice_controller.py
rpg_dice_roller/src/models/dice_input.py
rpg_dice_roller/src/models/errors.py
RPG_Dice_Roller-1.1.3.dist-info/METADATA
RPG_Dice_Roller-1.1.3.dist-info/WHEEL
RPG_Dice_Roller-1.1.3.dist-info/top_level.txt
RPG_Dice_Roller-1.1.3.dist-info/RECORD
