Metadata-Version: 2.1
Name: RPG-Dice-Roller
Version: 1.1.3
Author: Milton Ávila
License: MIT License
Requires-Python: >=3.9.4
